parsec/__init__.py
parsec/combinator.py
parsec/context.py
parsec/core.py
parsec/error.py
parsec/utils.py
parsec/text/__init__.py
parsec/text/basic.py
parsec/text/context.py
parsec/text/lex.py
parsec_python-0.1.1.dist-info/licenses/LICENSE
parsec_python-0.1.1.dist-info/METADATA
parsec_python-0.1.1.dist-info/WHEEL
parsec_python-0.1.1.dist-info/top_level.txt
parsec_python-0.1.1.dist-info/RECORD
