Metadata-Version: 2.4
Name: parsec-python
Version: 0.1.1
Summary: A Monadic Parser Combinator for Python.
Author-email: luminox <lunex_nocty@qq.com>
License-Expression: LGPL-2.1
Project-URL: Homepage, https://github.com/lunexnocty/parsec-python
Project-URL: Issues, https://github.com/lunexnocty/parsec-python/issues
Classifier: Development Status :: 3 - Alpha
Classifier: Topic :: Software Development :: Libraries
Classifier: Intended Audience :: Developers
Classifier: Operating System :: OS Independent
Classifier: Typing :: Typed
Requires-Python: >=3.13
License-File: LICENSE
Dynamic: license-file
